comp_arch/hw2a/full_adder_nodelay.v
// Implementation of a full addder

//   Inputs: A, B, Cin bits
//   Outputs: sum bit S, carry out bit Cout
//
module full_adder_nodelay(A, B, Cin, S, Cout);

   input A, B, Cin;
   output S, Cout;

   assign S = A ^ B ^ Cin;
   assign Cout = (A & B) | (A & Cin) | (B & Cin);

endmodule // full_adder_nodelay

comp_arch/hw2a/four_bit_adder_subtractor.v
// Include our full adder source file.
`include "full_adder_nodelay.v"

// Define a four-bit ripple carry adder.
//
//  Inputs: 4-bit numbers A and B, and Operation
//       For the operation, 0 means addition
//                          1 means subtraction
//  Outputs: 4-bit sum S, carry out bit Cout
//
module four_bit_adder_subtractor(A, B, Op, S, Cout);

   // Note the special syntax here to tell the Verilog compiler that A
   // and B are not single-bit values, but 4-bit values.  These are
   // known as arrays in verilog. The 3:0 here indicates we will index
   // the bits of A and B from three (MSB) down to zero (LSB).
   input [3:0]  A;
   input [3:0]  B;
   input        Op;

   // Similarly, S is a four-bit output. Cout is a one-bit output
   output [3:0] S;
   output       Cout;

   // We need three wires to transmit the carry bits between
   // the individual full adders.
   wire         C1, C2, C3;
   wire [3:0] B_XOR;

   xor (B_XOR[0], B[0], Op);
   xor (B_XOR[1], B[1], Op);
   xor (B_XOR[2], B[2], Op);
   xor (B_XOR[3], B[3], Op);
    
   // Here we are just instantiating four separate full adder modules
   // connected by wires.
   full_adder_nodelay FA1(A[0], B_XOR[0], 1'b0, S[0], C1);
   full_adder_nodelay FA2(A[1], B_XOR[1], C1,  S[1], C2);
   full_adder_nodelay FA3(A[2], B_XOR[2], C2,  S[2], C3);
   full_adder_nodelay FA4(A[3], B_XOR[3], C3,  S[3], Cout);
   
endmodule // four_bit_rca_nodelay

comp_arch/hw2a/adder_subtractor_test.v
// Test bench to compare timing for ripple carry adder and carry
// lookahead adder with simulated propagation delays. 

// Tell Icarus Verilog compiler what our timescale is (to interpret
// delay statements).
`timescale 1ns/100ps
`default_nettype none

// Include the module source file for the adder/subtractor
`include "four_bit_adder_subtractor.v"

// Define our testbench module:
module adder_subtractor_test();


   // Set up two 4-bit registers A & B for our addends.
   reg signed [3:0]  A = 4'b0;
   reg signed [3:0]  B = 4'b0;

   // And one for Cin (we will leave it at zero, however).
   reg        Op = 0;

   // Set up two different 4-bit wires to hold results of sums: one
   // expected result from built-in Verilog arithmetic, and one 
   // and one from your module
   wire [3:0] S_expected;
   wire [3:0] S_actual;

   // We're going to ignore Cout here in our tests, but we need to
   // define it as an output of our adder/subtractor.
   wire       Cout;

   task check;
      input op;
      input signed [3:0] a;
      input signed [3:0] b;
      input signed [3:0] actual;
      input signed [3:0] expected;
      if (expected !== actual) begin 
         $display("When %s %d and %d, got %d, but expected %d", op?"subtracting":"adding", a,b,actual,expected); 
      end
   endtask

   task test;
      input op;
      input signed [3:0] a;
      input signed [3:0] b;
      begin
         #20 A = a; B = b; Op = op;
         #20 check(op, a, b, S_actual, S_expected);
      end
   endtask
   
   // The syntax (x ? y : z) here evaluates to "y if x is true, and z otherwise"
   assign {S_expected} = Op ? A - B : A + B;

   // Instantiate our module for adder/subtractor
   four_bit_adder_subtractor adder(A, B, Op, S_actual, Cout);

   // This is the behavioral verilog segment to actually run our
   // tests. Note we are just setting values of A and B every 20 ticks
   // of the clock, and then finishing.
   initial begin

      $dumpfile("adder_subtractor_test.vcd");
      $dumpvars(0, adder_subtractor_test);

      #20 test(0, 1, 1);
      #20 test(1, 1, 1);
      #20 test(0, 2, 5);
      #20 test(1, 2, 5);
      #20 test(0, 4, -4);
      #20 test(1, 4, -4);
      #20 test(0, 7, 7); 
      #20 test(1, 7, 7); 
      #20 test(1, 7, 4); 
      #20 test(1, 7, 0); 
      #20 test(1, 3, 0); 
      
      #20 $finish;

   end

endmodule

comp_arch/hw2a/adder_subtractor_test.vcd
$date
	Fri Feb  9 23:24:01 2024
$end
$version
	Icarus Verilog
$end
$timescale
	100ps
$end
$scope module adder_subtractor_test $end
$var wire 4 ! S_expected [3:0] $end
$var wire 4 " S_actual [3:0] $end
$var wire 1 # Cout $end
$var reg 4 $ A [3:0] $end
$var reg 4 % B [3:0] $end
$var reg 1 & Op $end
$scope module adder $end
$var wire 4 ' A [3:0] $end
$var wire 4 ( B [3:0] $end
$var wire 1 & Op $end
$var wire 4 ) S [3:0] $end
$var wire 1 # Cout $end
$var wire 1 * C3 $end
$var wire 1 + C2 $end
$var wire 1 , C1 $end
$var wire 4 - B_XOR [3:0] $end
$scope module FA1 $end
$var wire 1 . A $end
$var wire 1 / B $end
$var wire 1 0 Cin $end
$var wire 1 , Cout $end
$var wire 1 1 S $end
$upscope $end
$scope module FA2 $end
$var wire 1 2 A $end
$var wire 1 3 B $end
$var wire 1 , Cin $end
$var wire 1 + Cout $end
$var wire 1 4 S $end
$upscope $end
$scope module FA3 $end
$var wire 1 5 A $end
$var wire 1 6 B $end
$var wire 1 + Cin $end
$var wire 1 * Cout $end
$var wire 1 7 S $end
$upscope $end
$scope module FA4 $end
$var wire 1 8 A $end
$var wire 1 9 B $end
$var wire 1 * Cin $end
$var wire 1 # Cout $end
$var wire 1 : S $end
$upscope $end
$upscope $end
$scope task check $end
$var reg 4 ; a [3:0] $end
$var reg 4 < actual [3:0] $end
$var reg 4 = b [3:0] $end
$var reg 4 > expected [3:0] $end
$var reg 1 ? op $end
$upscope $end
$scope task test $end
$var reg 4 @ a [3:0] $end
$var reg 4 A b [3:0] $end
$var reg 1 B op $end
$upscope $end
$upscope $end
$enddefinitions $end
$comment Show the parameter values. $end
$dumpall
$end
#0
$dumpvars
xB
bx A
bx @
x?
bx >
bx =
bx <
bx ;
0:
09
08
07
06
05
04
03
02
01
00
0/
0.
b0 -
0,
0+
0*
b0 )
b0 (
b0 '
0&
b0 %
b0 $
0#
b0 "
b0 !
$end
#200
b1 A
b1 @
0B
#400
14
1,
1/
b10 "
b10 )
01
b1 -
b10 !
1.
b1 %
b1 (
b1 $
b1 '
#600
b10 >
b10 <
b1 =
b1 ;
0?
#800
1B
#1000
0#
0*
0,
11
14
0+
17
b1111 "
b1111 )
1:
b0 !
0/
13
16
19
b1110 -
1&
#1200
b0 >
b1111 <
1?
#1400
b101 A
b10 @
0B
#1600
0*
17
0:
0+
11
b111 "
b111 )
14
1/
03
09
b111 !
b101 -
0.
12
0&
b101 %
b101 (
b10 $
b10 '
#1800
b111 >
b111 <
b101 =
b10 ;
0?
#2000
1B
#2200
1+
01
04
17
b1100 "
b1100 )
1:
b1101 !
0/
13
06
19
b1010 -
1&
#2400
b1101 >
b1100 <
1?
#2600
b1100 A
b100 @
0B
#2800
1#
0:
0+
1*
04
b0 "
b0 )
07
03
16
b0 !
b1100 -
02
15
0&
b1100 %
b1100 (
b100 $
b100 '
#3000
b0 >
b0 <
b1100 =
b100 ;
0?
#3200
1B
#3400
0*
11
14
17
b111 "
b111 )
0:
0#
b1000 !
1/
13
06
09
b11 -
1&
#3600
b1000 >
b111 <
1?
#3800
b111 A
b111 @
0B
#4000
1:
1*
1,
1+
01
b1110 "
b1110 )
14
16
b1110 !
b111 -
1.
12
0&
b111 %
b111 (
b111 $
b111 '
#4200
b1110 >
b1110 <
b111 =
b111 ;
0?
#4400
1B
#4600
0*
0+
0,
11
14
17
b1111 "
b1111 )
1:
0#
b0 !
0/
03
06
19
b1000 -
1&
#4800
b0 >
b1111 <
1?
#5000
b100 A
#5200
1#
0:
1*
07
1,
1+
01
b10 "
b10 )
14
1/
13
b11 !
b1011 -
b100 %
b100 (
#5400
b11 >
b10 <
b100 =
#5600
b0 A
#5800
b110 "
b110 )
17
16
b111 !
b1111 -
b0 %
b0 (
#6000
b111 >
b110 <
b0 =
#6200
b11 @
#6400
b10 "
b10 )
07
b11 !
05
b11 $
b11 '
#6600
b11 >
b10 <
b11 ;
