comp_arch/hw2b/binary_to_gray.v
module binary_to_gray (
    input [3:0] B,
    output [3:0] G
);

// Assign MSB directly
assign G[3] = B[3];

// Connect remaining bits with XOR operations
assign G[2] = B[2] ^ B[3];
assign G[1] = B[1] ^ B[2];
assign G[0] = B[0] ^ B[1];

endmodule

comp_arch/hw2b/binary_to_gray_tb.v
// Verilog test bench for E15 homework 5 problem 3.

`timescale 1ns/100ps
`default_nettype none
`include "binary_to_gray.v"

module binary_to_gray_tb;

   wire [3:0] B;
   wire [3:0] G;
   integer k=0;

   assign B = k;
   binary_to_gray the_circuit(B, G);

   initial begin

      $dumpfile("binary_to_gray.vcd");
      $dumpvars(0, binary_to_gray_tb);

      for (k=0; k<16; k=k+1)
        #10 $display("done testing case %d", k);

      $finish;

   end 
endmodule

comp_arch/hw2b/binary_to_gray.vcd
$date
	Fri Feb  9 22:33:58 2024
$end
$version
	Icarus Verilog
$end
$timescale
	100ps
$end
$scope module binary_to_gray_tb $end
$var wire 4 ! G [3:0] $end
$var wire 4 " B [3:0] $end
$var integer 32 # k [31:0] $end
$scope module the_circuit $end
$var wire 4 $ B [3:0] $end
$var wire 4 % G [3:0] $end
$upscope $end
$upscope $end
$enddefinitions $end
$comment Show the parameter values. $end
$dumpall
$end
#0
$dumpvars
b0 %
b0 $
b0 #
b0 "
b0 !
$end
#100
b1 !
b1 %
b1 "
b1 $
b1 #
#200
b11 !
b11 %
b10 "
b10 $
b10 #
#300
b10 !
b10 %
b11 "
b11 $
b11 #
#400
b110 !
b110 %
b100 "
b100 $
b100 #
#500
b111 !
b111 %
b101 "
b101 $
b101 #
#600
b101 !
b101 %
b110 "
b110 $
b110 #
#700
b100 !
b100 %
b111 "
b111 $
b111 #
#800
b1100 !
b1100 %
b1000 "
b1000 $
b1000 #
#900
b1101 !
b1101 %
b1001 "
b1001 $
b1001 #
#1000
b1111 !
b1111 %
b1010 "
b1010 $
b1010 #
#1100
b1110 !
b1110 %
b1011 "
b1011 $
b1011 #
#1200
b1010 !
b1010 %
b1100 "
b1100 $
b1100 #
#1300
b1011 !
b1011 %
b1101 "
b1101 $
b1101 #
#1400
b1001 !
b1001 %
b1110 "
b1110 $
b1110 #
#1500
b1000 !
b1000 %
b1111 "
b1111 $
b1111 #
#1600
b0 !
b0 %
b0 "
b0 $
b10000 #
